ptc/__init__.py
ptc/ptc.py
polish_tax_calculator-0.6.dist-info/METADATA
polish_tax_calculator-0.6.dist-info/WHEEL
polish_tax_calculator-0.6.dist-info/entry_points.txt
polish_tax_calculator-0.6.dist-info/top_level.txt
polish_tax_calculator-0.6.dist-info/RECORD
