Metadata-Version: 2.1
Name: polish-tax-calculator
Version: 0.6
Summary: Kalulator podatkowy dla działalności gospodarczej w formie CLI
Home-page: UNKNOWN
Author: Kamil Hark
License: MIT
Platform: UNKNOWN
Requires-Python: >=3.6
Requires-Dist: Click
